catenator/__init__.py
catenator/catenator.py
catenator-0.2.6.dist-info/LICENSE
catenator-0.2.6.dist-info/METADATA
catenator-0.2.6.dist-info/WHEEL
catenator-0.2.6.dist-info/entry_points.txt
catenator-0.2.6.dist-info/top_level.txt
catenator-0.2.6.dist-info/RECORD
