Metadata-Version: 2.1
Name: catenator
Version: 0.2.6
Summary: A Python tool for concatenating code.
Home-page: https://github.com/philiporange/catenator
Author: Philip Orange
Author-email: git@philiporange.com
Classifier: Development Status :: 3 - Alpha
Classifier: Intended Audience :: Developers
Classifier: License :: CC0 1.0 Universal (CC0 1.0) Public Domain Dedication
Classifier: Operating System :: OS Independent
Classifier: Programming Language :: Python :: 3
Classifier: Programming Language :: Python :: 3.6
Classifier: Programming Language :: Python :: 3.7
Classifier: Programming Language :: Python :: 3.8
Classifier: Programming Language :: Python :: 3.9
Requires-Python: >=3.6
License-File: LICENSE
Requires-Dist: pyperclip
Requires-Dist: watchdog
Provides-Extra: token_counting
Requires-Dist: tiktoken ; extra == 'token_counting'
